[
    {
        "1":"Каким принципом исторического позания является данное определение?: \n Рассмотрение фактов, событий в соответсвии с конкретной исторической обстановкой, во взаимосвязи, взаимообусловленности в развитии.",
        "2":"Сколько стихотворных строк составляет общий объем трех частей эпоса \"Манас\", записанных у Саякбая Каралаева?",
        "3":"Какой из этапов не относится к древнему каменному веку?",
        "4":"Какой из этапов не относится к позднему каменному веку?",
        "5":"Кем сформулирована наиболее аргументированная \"трудовая теория\" происхождения человека?",
        "6":"В какоим из этапов люди освоили огонь?",
        "7":"В каком из этапов люди приручили первое животное - собаку и утвердили патриархальные семьи и развитие родовой общины?",
        "8":"Как называли племена, которые населяли обширные территории, занимаемые современными государствами Средней Азии и Казахстаном в VIII-III вв. до н.э в древнеперсидских клинописных текстах?",
        "9":"С кем саки тиграхауда вступают в ожесточенную борьбу за независимостьв VII в. до н.э?",
        "10":"В каком году Кир II выступил во главе огромного 200-тысячного войска, в поход для покорения саков тиграхауда?",
        "11":"Кто возглавил саков тиграхауда во время похода Кира II против них в 530 г. до н.э?",
        "12":"Кто возглавил хуннские племена и за короткий срок создал мощную армию в конце III в. до н.э?",
        "13":"Кто возглавил Южную группу хуннов после поражения над китайцами в 56 г. до н.э?",
        "14":"Столица государства усуней...",
        "15":"В каком веке государство Давань оказалось в составе тюркского каганата?"
    },
    {
        "1": {
            "a": "Объективность",
            "b": "Социальный подход",
            "c": "Историзм",
            "d": "Альтернативность"
        },
        "2": {
            "a": "500 тысяч",
            "b": "350 тысяч",
            "c": "400 тысяч",
            "d": "600 тысяч"
        },
        "3": {
            "a": "Энеолит",
            "b": "Ранний палеолит",
            "c": "Средний палеолит",
            "d": "Поздний палеолит"
        },
        "4": {
            "a": "Мезолит",
            "b": "Поздний палеолит",
            "c": "Неолит",
            "d": "Энеолит"
        },
        "5": {
            "a": "Ч. Дарвином",
            "b": "З. Фрейдом",
            "c": "Ф. Энгельсом",
            "d": "Д. Моррисом"
        },
        "6": {
            "a": "Ранний палеолит",
            "b": "Поздний палеолит",
            "c": "Мезолит",
            "d": "Неолит"
        },
        "7": {
            "a": "Энеолит",
            "b": "Поздний палеолит",
            "c": "Неолит",
            "d": "Мезолит"
        },
        "8": {
            "a": "Карлуки",
            "b": "Гунны",
            "c": "Усуни",
            "d": "Саки"
        },
        "9": {
            "a": "Томирис",
            "b": "Кир II",
            "c": "Дарий I",
            "d": "Александр Македонский"
        },
        "10": {
            "a": "В 526 г. до н.э",
            "b": "В 518 г. до н.э",
            "c": "В 530 г. до н.э",
            "d": "В 610 г. до н.э"
        },
        "11": {
            "a": "Царь Мугуа",
            "b": "Модэ шаньюй",
            "c": "Дарий I",
            "d": "Томирис"
        },
        "12": {
            "a": "Томирис",
            "b": "Модэ шаньюй",
            "c": "Чжи-Чжи",
            "d": "Тон-джагбу"
        },
        "13": {
            "a": "Модэ шаньюй",
            "b": "шаньюй Хуанье",
            "c": "Чжи-Чжи",
            "d": "Ли Гаунли"
        },
        "14": {
            "a": "Чигу (Чигучен)",
            "b": "Суяб",
            "c": "Эрши",
            "d": "Чач"
        },
        "15": {
            "a": "В VII в н.э",
            "b": "В V в до н.э",
            "c": "В IV в до н.э",
            "d": "В VI в. н.э"
        }
    },
    {
        "1": "Историзм",
        "2": "500 тысяч",
        "3": "Энеолит",
        "4": "Поздний палеолит",
        "5": "Ф. Энгельсом",
        "6": "Ранний палеолит",
        "7": "Мезолит",
        "8": "Саки",
        "9": "Кир II",
        "10": "В 530 г. до н.э",
        "11": "Томирис",
        "12": "Модэ шаньюй",
        "13": "шаньюй Хуанье",
        "14": "Чигу (Чигучен)",
        "15": "В VI в. н.э"
    }
]